{
  "console": "nintendinho",
  "generated_at": "2026-02-11T22:38:02.799774",
  "rom_count": 1,
  "items": [
    {
      "rom": "E:\\NINTEDINHO\\Advanced Dungeons & Dragons - Dragon Strike (U) [h1]_emulabr.com\\Advanced Dungeons & Dragons - Dragon Strike (U) [h1].nes",
      "crc32": "5A786D4F",
      "output_dir": "export\\universal_batch_v2\\nintendinho\\Advanced Dungeons _ Dragons - Dragon Strike (U) _h1__5A786D4F",
      "status": "ok",
      "reason": "pure_jsonl_generated",
      "returncode": 0,
      "pure_jsonl_count": 1,
      "report_count": 1
    }
  ]
}